[
    {
        "question": "¿Qué significa HTML?",
        "options": [
            "HyperText Markup Language",
            "HighText Machine Language",
            "HyperTabular Markup Language",
            "HyperTool Multi Language"
        ],
        "correctAnswer": "HyperText Markup Language"
    },
    {
        "question": "¿Qué lenguaje se usa principalmente para estilos en páginas web?",
        "options": [
            "CSS",
            "Java",
            "Python",
            "C++"
        ],
        "correctAnswer": "CSS"
    },
    {
        "question": "¿Cuál de estos NO es un lenguaje de programación?",
        "options": [
            "HTML",
            "Python",
            "JavaScript",
            "Java"
        ],
        "correctAnswer": "HTML"
    },
    {
        "question": "¿Qué operador se usa para asignación en JavaScript?",
        "options": [
            "=",
            "==",
            "===",
            ":="
        ],
        "correctAnswer": "="
    },
    {
        "question": "¿Qué estructura de control repite un bloque de código mientras una condición sea verdadera?",
        "options": [
            "while",
            "if",
            "switch",
            "break"
        ],
        "correctAnswer": "while"
    },
    {
        "question": "¿Qué comando se usa en Git para clonar un repositorio?",
        "options": [
            "git clone",
            "git pull",
            "git push",
            "git init"
        ],
        "correctAnswer": "git clone"
    },
    {
        "question": "¿Qué tipo de lenguaje es Python?",
        "options": [
            "Interpretado",
            "Compilado",
            "Ensamblador",
            "Binario"
        ],
        "correctAnswer": "Interpretado"
    },
    {
        "question": "¿Qué significa API?",
        "options": [
            "Application Programming Interface",
            "Advanced Programming Input",
            "Application Protocol Interface",
            "Applied Program Integration"
        ],
        "correctAnswer": "Application Programming Interface"
    },
    {
        "question": "¿Cuál es la extensión de archivo correcta para un archivo de JavaScript?",
        "options": [
            ".js",
            ".java",
            ".javascript",
            ".jv"
        ],
        "correctAnswer": ".js"
    },
    {
        "question": "¿Qué método se usa para imprimir en consola en JavaScript?",
        "options": [
            "console.log()",
            "print()",
            "echo()",
            "display()"
        ],
        "correctAnswer": "console.log()"
    }
]